semantic_scholar/__init__.py
semantic_scholar/py.typed
semantic_scholar/semantic_scholar.py
semantic_scholar/api/__init__.py
semantic_scholar/api/base.py
semantic_scholar/api/clients.py
semantic_scholar/api/exceptions.py
semantic_scholar/api/retry.py
semantic_scholar/models/__init__.py
semantic_scholar/models/author.py
semantic_scholar/models/base.py
semantic_scholar/models/common.py
semantic_scholar/models/dataset.py
semantic_scholar/models/paper.py
semantic_scholar/models/snippet.py
semantic_scholar_api-0.2.0.dist-info/METADATA
semantic_scholar_api-0.2.0.dist-info/WHEEL
semantic_scholar_api-0.2.0.dist-info/licenses/LICENSE
semantic_scholar_api-0.2.0.dist-info/RECORD
