Metadata-Version: 2.4
Name: semantic-scholar-api
Version: 0.2.0
Summary: Python client for the Semantic Scholar API
Project-URL: Homepage, https://github.com/bguisard/semantic-scholar-api
Project-URL: Repository, https://github.com/bguisard/semantic-scholar-api
Project-URL: Documentation, https://github.com/bguisard/semantic-scholar-api#readme
Author: Bruno Guisard
License-File: LICENSE
Requires-Python: >=3.11
Requires-Dist: httpx>=0.28.1
Requires-Dist: pydantic>=2.10.6
Requires-Dist: tenacity>=9.0.0
